libwc24tools/__init__.py
libwc24tools/wc24encrypt.py
libwc24tools-0.0.2.dist-info/LICENSE
libwc24tools-0.0.2.dist-info/METADATA
libwc24tools-0.0.2.dist-info/WHEEL
libwc24tools-0.0.2.dist-info/top_level.txt
libwc24tools-0.0.2.dist-info/RECORD
