Metadata-Version: 2.1
Name: libwc24tools
Version: 0.0.2
Summary: Encrypt a WiiConnect24 file
Home-page: https://github.com/6100m/libwc24tools
Author: Larsenv/6100m/SketchMaster2001
Author-email: sketch@wiilink24.com
License: UNKNOWN
Project-URL: Bug Tracker, https://github.com/6100m/libwc24tools/issues
Platform: UNKNOWN
Classifier: Programming Language :: Python :: 3
Requires-Python: >=3.7
License-File: LICENSE
Requires-Dist: nlzss
Requires-Dist: pycryptodome
Requires-Dist: rsa
